{
  "lastUpdated": "2026-04-26T06:00:45.995Z",
  "totalVideos": 50,
  "totalViews": 3173,
  "avgViews": 63,
  "videos": [
    {
      "videoId": "SqL3ixqUsVs",
      "title": "3 Reasons You Keep Failing Funded Challenges (ICT Trader Mistakes)",
      "publishedAt": "2026-04-18T05:01:00Z",
      "views": 366,
      "likes": 8,
      "comments": 0,
      "retention": 0
    },
    {
      "videoId": "vWKYXVAf6p4",
      "title": "3 Mistakes That Kill Funded Accounts (Fix These Now)",
      "publishedAt": "2026-04-21T05:00:35Z",
      "views": 290,
      "likes": 5,
      "comments": 0,
      "retention": 0
    },
    {
      "videoId": "cn6oo1U3Bf8",
      "title": "The One Fair Value Gap Filter That Actually Works (2026)",
      "publishedAt": "2026-04-19T17:01:06Z",
      "views": 265,
      "likes": 4,
      "comments": 0,
      "retention": 0
    },
    {
      "videoId": "T1oFo4OMSjg",
      "title": "Can You Spot a Fair Value Gap? 🧠 ICT Quiz",
      "publishedAt": "2026-04-18T17:00:43Z",
      "views": 259,
      "likes": 5,
      "comments": 0,
      "retention": 0
    },
    {
      "videoId": "rzHHTgvZ7Bo",
      "title": "POV: You Finally Understand Fair Value Gaps",
      "publishedAt": "2026-04-17T11:00:40Z",
      "views": 211,
      "likes": 6,
      "comments": 0,
      "retention": 0
    },
    {
      "videoId": "jLC_WY6zYLg",
      "title": "Why Smart Money Traps Retail at Every Swing High (2026)",
      "publishedAt": "2026-04-20T05:00:33Z",
      "views": 209,
      "likes": 2,
      "comments": 0,
      "retention": 0
    },
    {
      "videoId": "sSmgZtwk7ZU",
      "title": "Silver Bullet Myth That's Killing Your Funded Account (2026)",
      "publishedAt": "2026-04-19T08:52:57Z",
      "views": 190,
      "likes": 2,
      "comments": 0,
      "retention": 0
    },
    {
      "videoId": "DTXaHLpFQVg",
      "title": "I Blew My Funded Account Ignoring This One Thing",
      "publishedAt": "2026-04-17T17:01:13Z",
      "views": 181,
      "likes": 3,
      "comments": 0,
      "retention": 0
    },
    {
      "videoId": "JTN7zzqGqt4",
      "title": "This Order Block Setup Made 3R In One Trade",
      "publishedAt": "2026-04-17T05:00:55Z",
      "views": 142,
      "likes": 3,
      "comments": 0,
      "retention": 0
    },
    {
      "videoId": "g3yxOUiAvlI",
      "title": "This Fair Value Gap Setup Paid Me $4,200 In One Trade",
      "publishedAt": "2026-04-18T11:01:05Z",
      "views": 140,
      "likes": 1,
      "comments": 0,
      "retention": 0
    },
    {
      "videoId": "b_ikGu3BDOc",
      "title": "Stop Trading Fair Value Gaps Like This",
      "publishedAt": "2026-04-19T05:00:56Z",
      "views": 127,
      "likes": 1,
      "comments": 0,
      "retention": 0
    },
    {
      "videoId": "X88xbyvnkAM",
      "title": "3 Order Block Mistakes Killing Your Funded Account (2026)",
      "publishedAt": "2026-04-19T11:35:30Z",
      "views": 107,
      "likes": 2,
      "comments": 0,
      "retention": 0
    },
    {
      "videoId": "rFI3HIhsCsA",
      "title": "90% of Traders Get This Wrong — Do You Know the Answer?",
      "publishedAt": "2026-04-20T17:00:48Z",
      "views": 105,
      "likes": 2,
      "comments": 0,
      "retention": 0
    },
    {
      "videoId": "XBRq7aB4bJc",
      "title": "Why Trading Is IMPOSSIBLE (The Truth)",
      "publishedAt": "2026-04-07T05:15:14Z",
      "views": 100,
      "likes": 1,
      "comments": 0,
      "retention": 0
    },
    {
      "videoId": "lI6dvvGuRSI",
      "title": "The Indicator Lie That's Keeping Traders Broke (2026)",
      "publishedAt": "2026-04-19T11:00:32Z",
      "views": 94,
      "likes": 0,
      "comments": 0,
      "retention": 0
    },
    {
      "videoId": "sVRWHdxLX0A",
      "title": "POV: You Pass Your Funded Account Then GDP Drops 🔴",
      "publishedAt": "2026-04-22T17:01:01Z",
      "views": 71,
      "likes": 1,
      "comments": 0,
      "retention": 0
    },
    {
      "videoId": "JD8RiIQ3RPo",
      "title": "Retail Trader vs Smart Money: Who Wins?",
      "publishedAt": "2026-04-16T17:00:51Z",
      "views": 55,
      "likes": 0,
      "comments": 0,
      "retention": 0
    },
    {
      "videoId": "K46RigBkrLg",
      "title": "The Biggest GDP Trading Myth (That's Costing You Money in 2026)",
      "publishedAt": "2026-04-23T05:00:56Z",
      "views": 42,
      "likes": 0,
      "comments": 0,
      "retention": 0
    },
    {
      "videoId": "O7RojzdCnh8",
      "title": "I Blew 3 Funded Accounts Before Learning This One Thing (2026)",
      "publishedAt": "2026-04-21T11:01:01Z",
      "views": 40,
      "likes": 2,
      "comments": 0,
      "retention": 0
    },
    {
      "videoId": "4m1AI5SgG9E",
      "title": "Monday's False Break Will Trap You (Unless You See This) | R2F Trading 2026",
      "publishedAt": "2026-04-22T11:00:47Z",
      "views": 22,
      "likes": 0,
      "comments": 0,
      "retention": 0
    },
    {
      "videoId": "ZB79mm667Eo",
      "title": "Why Do 90% of Retail Traders Lose? (Take the Quiz)",
      "publishedAt": "2026-04-21T17:00:58Z",
      "views": 22,
      "likes": 0,
      "comments": 0,
      "retention": 0
    },
    {
      "videoId": "_fcwdk_UIoM",
      "title": "The FVG Filter Nobody Teaches (2026)",
      "publishedAt": "2026-04-20T11:00:56Z",
      "views": 22,
      "likes": 0,
      "comments": 0,
      "retention": 0
    },
    {
      "videoId": "qWyJSjqyw8A",
      "title": "video idea 8be7c",
      "publishedAt": "2026-04-20T07:38:21Z",
      "views": 19,
      "likes": 1,
      "comments": 0,
      "retention": 0
    },
    {
      "videoId": "LWWPCw_PjdE",
      "title": "POV: You're Trading CPI Day Without This Setup",
      "publishedAt": "2026-04-09T05:13:32Z",
      "views": 15,
      "likes": 0,
      "comments": 0,
      "retention": 0
    },
    {
      "videoId": "aMhjBIBbcWI",
      "title": "League Acc",
      "publishedAt": "2025-12-07T02:07:26Z",
      "views": 15,
      "likes": 0,
      "comments": 0,
      "retention": 0
    },
    {
      "videoId": "SJbzMgxijEw",
      "title": "Trading is Simple BUT Not Easy - The Truth",
      "publishedAt": "2026-04-07T11:22:34Z",
      "views": 11,
      "likes": 1,
      "comments": 0,
      "retention": 0
    },
    {
      "videoId": "Xcq8GWEpNF8",
      "title": "6 months of CPI losses. Then I changed ONE thing.",
      "publishedAt": "2026-04-09T17:15:13Z",
      "views": 9,
      "likes": 0,
      "comments": 0,
      "retention": 0
    },
    {
      "videoId": "4x-lHEFZEh4",
      "title": "Stop Chasing Every Setup. Here's What Actually Made Me Profitable.",
      "publishedAt": "2026-04-06T12:11:56Z",
      "views": 7,
      "likes": 0,
      "comments": 0,
      "retention": 0
    },
    {
      "videoId": "lZ4yErbwKWk",
      "title": "5 Risk Management Rules That Save Trading Accounts",
      "publishedAt": "2026-04-05T10:09:34Z",
      "views": 7,
      "likes": 1,
      "comments": 0,
      "retention": 0
    },
    {
      "videoId": "kcaUOrlp89I",
      "title": "Dune Run",
      "publishedAt": "2026-04-20T13:46:50Z",
      "views": 6,
      "likes": 0,
      "comments": 0,
      "retention": 0
    },
    {
      "videoId": "wiSkHa_cLzQ",
      "title": "CPI Trading Quiz: Can You Spot Smart Money's Move?",
      "publishedAt": "2026-04-08T11:47:11Z",
      "views": 5,
      "likes": 0,
      "comments": 0,
      "retention": 0
    },
    {
      "videoId": "PZpz4MjTzrg",
      "title": "I Lost $10K Before Learning This CPI Trading Secret",
      "publishedAt": "2026-04-10T17:16:03Z",
      "views": 4,
      "likes": 0,
      "comments": 0,
      "retention": 0
    },
    {
      "videoId": "Wgnh_TaoGyY",
      "title": "Can You Spot the Fair Value Gap? Test Your ICT Skills",
      "publishedAt": "2026-04-10T11:16:07Z",
      "views": 4,
      "likes": 0,
      "comments": 0,
      "retention": 0
    },
    {
      "videoId": "k2xegnt52do",
      "title": "Stop Trading CPI Like This (Funded Traders Know Better)",
      "publishedAt": "2026-04-08T05:12:07Z",
      "views": 3,
      "likes": 0,
      "comments": 0,
      "retention": 0
    },
    {
      "videoId": "9K_-Ve8Ljcc",
      "title": "The More I Waited, The More I Won",
      "publishedAt": "2026-04-06T10:12:28Z",
      "views": 3,
      "likes": 0,
      "comments": 0,
      "retention": 0
    },
    {
      "videoId": "kAoDAAdGpf8",
      "title": "Stop Chasing Order Blocks on CPI Day - Here's What Smart Money Actually Does",
      "publishedAt": "2026-04-11T17:45:06Z",
      "views": 2,
      "likes": 0,
      "comments": 0,
      "retention": 0
    },
    {
      "videoId": "nZusqhn-SSI",
      "title": "3 Trading Mistakes That Cost Me Thousands",
      "publishedAt": "2026-04-06T11:11:16Z",
      "views": 2,
      "likes": 0,
      "comments": 0,
      "retention": 0
    },
    {
      "videoId": "oOvy2Vc0YOA",
      "title": "POV: You Realize Why Your ICT Setups Keep Failing",
      "publishedAt": "2026-04-06T03:32:02Z",
      "views": 1,
      "likes": 0,
      "comments": 0,
      "retention": 0
    },
    {
      "videoId": "cnyESYAaxYk",
      "title": "Nov 18  1059 29s 202511181252 ny3zg",
      "publishedAt": "2025-11-18T05:52:51Z",
      "views": 0,
      "likes": 0,
      "comments": 0,
      "retention": 0
    },
    {
      "videoId": "OdSXrfbfR9g",
      "title": "Nov 17  1720 22s 202511172123 bxuo7",
      "publishedAt": "2025-11-18T02:59:55Z",
      "views": 0,
      "likes": 0,
      "comments": 0,
      "retention": 0
    },
    {
      "videoId": "mT8g-JspmGU",
      "title": "Nov 07  1002 36s 202511071036 1sp9k",
      "publishedAt": "2025-11-07T03:36:53Z",
      "views": 0,
      "likes": 0,
      "comments": 0,
      "retention": 0
    },
    {
      "videoId": "RccFFHgDOwk",
      "title": "Nov 06  1329 29s 202511061343 xwxvi",
      "publishedAt": "2025-11-06T06:43:52Z",
      "views": 0,
      "likes": 0,
      "comments": 0,
      "retention": 0
    },
    {
      "videoId": "Gu-LM9Z93hg",
      "title": "Nov 06  1117 29s 202511061206 q7hua",
      "publishedAt": "2025-11-06T05:07:02Z",
      "views": 0,
      "likes": 0,
      "comments": 0,
      "retention": 0
    },
    {
      "videoId": "uJktx3eAq1M",
      "title": "Nov 05  1058 22s 202511051312 cjf4p",
      "publishedAt": "2025-11-05T06:13:38Z",
      "views": 0,
      "likes": 0,
      "comments": 0,
      "retention": 0
    },
    {
      "videoId": "7nPW1jQmUtk",
      "title": "Nov 04  1735 29s 202511041749 5dopa",
      "publishedAt": "2025-11-05T02:23:58Z",
      "views": 0,
      "likes": 0,
      "comments": 0,
      "retention": 0
    },
    {
      "videoId": "DilBGMNX8DU",
      "title": "Nov 04  1435 29s 202511041530 xld2q",
      "publishedAt": "2025-11-04T08:31:01Z",
      "views": 0,
      "likes": 0,
      "comments": 0,
      "retention": 0
    },
    {
      "videoId": "eRfKXs-eVAg",
      "title": "Nov 03  1657 29s 202511041349 bgrkj",
      "publishedAt": "2025-11-04T06:49:27Z",
      "views": 0,
      "likes": 0,
      "comments": 0,
      "retention": 0
    },
    {
      "videoId": "ZyE7DR2ho90",
      "title": "Nov 02  1548 29s 202511021735 68ffl",
      "publishedAt": "2025-11-02T10:35:58Z",
      "views": 0,
      "likes": 0,
      "comments": 0,
      "retention": 0
    },
    {
      "videoId": "l3YmbxcR1t8",
      "title": "Nov 01  2041 42s 202511012150 spzs4",
      "publishedAt": "2025-11-01T14:52:00Z",
      "views": 0,
      "likes": 0,
      "comments": 0,
      "retention": 0
    },
    {
      "videoId": "lx3i-1uadd0",
      "title": "Oct 30  2039 22s 202510311140 phgfg",
      "publishedAt": "2025-10-31T04:40:51Z",
      "views": 0,
      "likes": 0,
      "comments": 0,
      "retention": 0
    }
  ]
}